<?xml version="1.0" encoding="UTF-8"?>
<con:soapui-project id="9c2200b7-df0f-4bc2-b73c-6fad5ae946b9" activeEnvironment="Default" name="REST Project 5" soapui-version="5.5.0" abortOnError="false" runType="SEQUENTIAL" xmlns:con="http://eviware.com/soapui/config"><con:settings/><con:interface xsi:type="con:RestService" id="5f3a2c87-8fc5-4a06-9252-6a732e149224" wadlVersion="http://wadl.dev.java.net/2009/02" name="http://development.mawashi.tools:8080" type="rest" xmlns:xsi="http://www.w3.org/2001/XMLSchema-instance"><con:settings/><con:definitionCache type="TEXT" rootPart=""/><con:endpoints><con:endpoint>http://development.mawashi.tools:8080</con:endpoint></con:endpoints><con:resource name="Signup" path="/api/rest/v1.0/auth/signup" id="d1bb1595-8db5-4bde-945f-b42871d318ef"><con:settings/><con:parameters/><con:method name="Signup 1" id="c0e20348-aecb-4497-ba6b-e3b647bcfd7c" method="POST"><con:settings/><con:parameters/><con:representation type="REQUEST"><con:mediaType>application/json</con:mediaType><con:params/></con:representation><con:representation type="FAULT"><con:mediaType>application/json</con:mediaType><con:status>400</con:status><con:params/><con:element xmlns:sig="http://development.mawashi.tools/api/rest/v1.0/auth/signup">sig:Fault</con:element></con:representation><con:representation type="RESPONSE"><con:mediaType>application/json</con:mediaType><con:status>201</con:status><con:params/><con:element xmlns:sig="http://development.mawashi.tools/api/rest/v1.0/auth/signup">sig:Response</con:element></con:representation><con:request name="Request 1" id="18cca023-5dd8-4067-bbaf-19467c207903" mediaType="application/json" postQueryString="false"><con:settings><con:setting id="com.eviware.soapui.impl.wsdl.WsdlRequest@request-headers">&lt;xml-fragment/></con:setting></con:settings><con:endpoint>http://development.mawashi.tools:8080</con:endpoint><con:request>{"username":"yulia3932@gmail.com","account":"qwertyu","password":"1234"}</con:request><con:originalUri>http://development.mawashi.tools/api/rest/v1.0/auth/signup</con:originalUri><con:credentials><con:authType>No Authorization</con:authType></con:credentials><con:jmsConfig JMSDeliveryMode="PERSISTENT"/><con:jmsPropertyConfig/><con:parameters/><con:parameterOrder/></con:request></con:method></con:resource></con:interface><con:interface xsi:type="con:RestService" id="ebe59ff3-74b4-4e1d-8d3d-aada9f030239" wadlVersion="http://wadl.dev.java.net/2009/02" name="http://development.mawashi.tools:8080" type="rest" xmlns:xsi="http://www.w3.org/2001/XMLSchema-instance"><con:settings/><con:definitionCache type="TEXT" rootPart=""/><con:endpoints><con:endpoint>http://development.mawashi.tools:8080</con:endpoint></con:endpoints><con:resource name="Signin" path="/api/rest/v1.0/auth/signin" id="63161fbd-a3e2-4b88-bd39-5c3884c8fdbb"><con:settings/><con:parameters/><con:method name="Signin 1" id="3247e3f6-77df-4f8b-9969-6bbbbf9545eb" method="POST"><con:settings/><con:parameters/><con:representation type="REQUEST"><con:mediaType>application/json</con:mediaType><con:params/></con:representation><con:representation type="RESPONSE"><con:mediaType>application/json</con:mediaType><con:status>200</con:status><con:params/><con:element xmlns:sig="http://development.mawashi.tools/api/rest/v1.0/auth/signin">sig:Response</con:element></con:representation><con:request name="Request 1" id="5dd0290e-517e-4c4e-b57e-1e7c38416550" mediaType="application/json" postQueryString="false"><con:settings><con:setting id="com.eviware.soapui.impl.wsdl.WsdlRequest@request-headers">&lt;xml-fragment/></con:setting></con:settings><con:endpoint>http://development.mawashi.tools:8080</con:endpoint><con:request>{"username":"yulia3932@gmail.com","account":"qwertyu","password":"1234"}</con:request><con:originalUri>http://development.mawashi.tools/api/rest/v1.0/auth/signin</con:originalUri><con:credentials><con:authType>No Authorization</con:authType></con:credentials><con:jmsConfig JMSDeliveryMode="PERSISTENT"/><con:jmsPropertyConfig/><con:parameters/><con:parameterOrder/></con:request></con:method></con:resource></con:interface><con:interface xsi:type="con:RestService" id="5b5732d4-7a03-4396-9980-378ce551f04a" wadlVersion="http://wadl.dev.java.net/2009/02" name="http://development.mawashi.tools:8080" type="rest" xmlns:xsi="http://www.w3.org/2001/XMLSchema-instance"><con:settings/><con:definitionCache type="TEXT" rootPart=""/><con:endpoints><con:endpoint>http://development.mawashi.tools:8080</con:endpoint></con:endpoints><con:resource name="V1.0" path="/api/rest/v1.0/" id="59a14b96-60f8-45c9-bf42-3c4365a46bc6"><con:settings/><con:parameters><con:parameter><con:name>Authorization</con:name><con:value/><con:style>HEADER</con:style><con:default/><con:description xsi:nil="true"/></con:parameter></con:parameters><con:resource name="projects" path="app/projects" id="7322f047-7c84-45f3-b8e9-23cbf7a739a1"><con:settings/><con:parameters/><con:method name="Method 1" id="10ee237d-25d1-4147-90c9-6b25d23ec495" method="GET"><con:settings/><con:parameters/><con:representation type="RESPONSE"><con:mediaType>application/json</con:mediaType><con:status>200</con:status><con:params/><con:element xmlns:proj="http://development.mawashi.tools/api/rest/v1.0/app/projects">proj:Response</con:element></con:representation><con:representation type="FAULT"><con:mediaType>application/json;charset=UTF-8</con:mediaType><con:status>401</con:status><con:params/><con:element xmlns:proj="http://development.mawashi.tools/api/rest/v1.0/app/projects">proj:Fault</con:element></con:representation><con:request name="Request 1" id="ec00c046-5148-4ad7-8216-02e449a7c89a" mediaType="application/json"><con:settings><con:setting id="com.eviware.soapui.impl.wsdl.WsdlRequest@request-headers">&lt;xml-fragment/></con:setting></con:settings><con:endpoint>http://development.mawashi.tools:8080</con:endpoint><con:request/><con:originalUri>http://development.mawashi.tools/api/rest/v1.0/app/projects</con:originalUri><con:credentials><con:authType>No Authorization</con:authType></con:credentials><con:jmsConfig JMSDeliveryMode="PERSISTENT"/><con:jmsPropertyConfig/><con:parameters><entry key="Authorization" value="Bearer eyJhbGciOiJIUzUxMiJ9.eyJzdWIiOiI3NyIsImlhdCI6MTU4Nzk5NzYwOCwiZXhwIjoxNTg4NjAyNDA4fQ.yhO7le_5MbnFsarV4m2fuzE8_maqPVSzKTPw_MUm06hwZgqDV6WLEmsw6MY0OHW3srHiKUNH97PWQRQ5LkOgdA" xmlns="http://eviware.com/soapui/config"/></con:parameters></con:request></con:method></con:resource><con:method name="V1.0 1" id="21c5f52c-77de-42f7-8b27-d0e5c2657e16" method="GET"><con:settings/><con:parameters/><con:representation type="RESPONSE"><con:mediaType>application/json</con:mediaType><con:status>200</con:status><con:params/><con:element xmlns:v1="http://development.mawashi.tools/api/rest/v1.0/">v1:Response</con:element></con:representation><con:representation type="FAULT"><con:mediaType>application/json;charset=UTF-8</con:mediaType><con:status>401</con:status><con:params/><con:element xmlns:v1="http://development.mawashi.tools/api/rest/v1.0/">v1:Fault</con:element></con:representation><con:request name="Request 1" id="ac365129-eb7f-49ee-8285-7bc7905f4f96" mediaType="application/json"><con:settings><con:setting id="com.eviware.soapui.impl.wsdl.WsdlRequest@request-headers">&lt;xml-fragment/></con:setting></con:settings><con:endpoint>http://development.mawashi.tools:8080</con:endpoint><con:request/><con:originalUri>http://development.mawashi.tools/api/rest/v1.0/</con:originalUri><con:credentials><con:authType>No Authorization</con:authType></con:credentials><con:jmsConfig JMSDeliveryMode="PERSISTENT"/><con:jmsPropertyConfig/><con:parameters><entry key="Authorization" value="Bearer eyJhbGciOiJIUzUxMiJ9.eyJzdWIiOiI3NyIsImlhdCI6MTU4Nzk5NzYwOCwiZXhwIjoxNTg4NjAyNDA4fQ.yhO7le_5MbnFsarV4m2fuzE8_maqPVSzKTPw_MUm06hwZgqDV6WLEmsw6MY0OHW3srHiKUNH97PWQRQ5LkOgdA" xmlns="http://eviware.com/soapui/config"/></con:parameters><con:parameterOrder><con:entry>Authorization</con:entry></con:parameterOrder></con:request></con:method></con:resource></con:interface><con:testSuite id="c4cfbecb-88ae-41f7-8f3c-8e9f281e2630" name="TestSuite 1"><con:settings/><con:runType>SEQUENTIAL</con:runType><con:testCase id="95fc4edc-0123-4168-bdf3-073cde41b20b" failOnError="true" failTestCaseOnErrors="true" keepSession="false" maxResults="0" name="signup" searchProperties="true"><con:settings/><con:testStep type="restrequest" name="signup" id="649cc628-fa9b-47a0-b400-dd44bb71d965"><con:settings/><con:config service="http://development.mawashi.tools:8080" resourcePath="/api/rest/v1.0/auth/signup" methodName="Signup 1" xsi:type="con:RestRequestStep" xmlns:xsi="http://www.w3.org/2001/XMLSchema-instance"><con:restRequest name="signup" id="18cca023-5dd8-4067-bbaf-19467c207903" mediaType="application/json" postQueryString="false"><con:settings><con:setting id="com.eviware.soapui.impl.wsdl.WsdlRequest@request-headers">&lt;xml-fragment/></con:setting></con:settings><con:endpoint>http://development.mawashi.tools:8080</con:endpoint><con:request>{"username":"yulia3932@gmail.com","account":"qwertyu","password":"1234"}</con:request><con:originalUri>http://development.mawashi.tools/api/rest/v1.0/auth/signup</con:originalUri><con:assertion type="Valid HTTP Status Codes" id="9afc0c1f-4962-428d-beb2-1a7b21ceab7f" name="Valid HTTP Status Codes"><con:configuration><codes>400</codes></con:configuration></con:assertion><con:credentials><con:authType>No Authorization</con:authType></con:credentials><con:jmsConfig JMSDeliveryMode="PERSISTENT"/><con:jmsPropertyConfig/><con:parameters/><con:parameterOrder/></con:restRequest></con:config></con:testStep><con:testStep type="transfer" name="Property Transfer1" id="a0793484-7c2e-4b3e-bca6-7ce9e7f8cced"><con:settings/><con:config xsi:type="con:PropertyTransfersStep" xmlns:xsi="http://www.w3.org/2001/XMLSchema-instance"><con:transfers setNullOnMissingSource="true" transferTextContent="true" failOnError="true" ignoreEmpty="false" transferToAll="false" entitize="false" transferChildNodes="false"><con:name>Bearer</con:name><con:sourceType>Response</con:sourceType><con:sourceStep>signup</con:sourceStep><con:targetType>Username</con:targetType><con:targetStep>signin</con:targetStep><con:type>JSONPATH</con:type><con:targetTransferType>JSONPATH</con:targetTransferType><con:upgraded>true</con:upgraded></con:transfers></con:config></con:testStep><con:testStep type="restrequest" name="signin" id="e98c0782-a261-41bf-8476-d18d076e0ec1"><con:settings/><con:config service="http://development.mawashi.tools:8080" resourcePath="/api/rest/v1.0/auth/signin" methodName="Signin 1" xsi:type="con:RestRequestStep" xmlns:xsi="http://www.w3.org/2001/XMLSchema-instance"><con:restRequest name="signin" id="5dd0290e-517e-4c4e-b57e-1e7c38416550" mediaType="application/json" postQueryString="false"><con:settings><con:setting id="com.eviware.soapui.impl.wsdl.WsdlRequest@request-headers">&lt;xml-fragment/></con:setting></con:settings><con:endpoint>http://development.mawashi.tools:8080</con:endpoint><con:request>{"username":"yulia3932@gmail.com","account":"qwertyu","password":"1234"}</con:request><con:originalUri>http://development.mawashi.tools/api/rest/v1.0/auth/signin</con:originalUri><con:assertion type="Valid HTTP Status Codes" id="cfd82af8-b6a2-4d08-bf5d-d3dbdc4db29f" name="Valid HTTP Status Codes"><con:configuration><codes>200</codes></con:configuration></con:assertion><con:credentials><con:username>{"success":false,"error":"Username is already registered with another account!","data":null}</con:username><con:password>{"success":false,"error":"Username is already registered with another account!","data":null}</con:password><con:authType>No Authorization</con:authType></con:credentials><con:jmsConfig JMSDeliveryMode="PERSISTENT"/><con:jmsPropertyConfig/><con:parameters/><con:parameterOrder/></con:restRequest></con:config></con:testStep><con:testStep type="transfer" name="Property Transfer2" id="8cfaf94c-4e39-4386-b1a7-83b08c4ec639"><con:settings/><con:config xsi:type="con:PropertyTransfersStep" xmlns:xsi="http://www.w3.org/2001/XMLSchema-instance"><con:transfers setNullOnMissingSource="true" transferTextContent="true" failOnError="true" ignoreEmpty="false" transferToAll="false" entitize="false" transferChildNodes="false"><con:name>Bearer</con:name><con:sourceType>Response</con:sourceType><con:sourceStep>signin</con:sourceStep><con:targetType>Authorization</con:targetType><con:targetStep>V1.0 1</con:targetStep><con:type>JSONPATH</con:type><con:targetTransferType>JSONPATH</con:targetTransferType><con:upgraded>true</con:upgraded></con:transfers></con:config></con:testStep><con:testStep type="restrequest" name="V1.0 1" id="e6fb7ea4-456b-4902-bb5a-6d203abeedd4"><con:settings/><con:config service="http://development.mawashi.tools:8080" resourcePath="/api/rest/v1.0/" methodName="V1.0 1" xsi:type="con:RestRequestStep" xmlns:xsi="http://www.w3.org/2001/XMLSchema-instance"><con:restRequest name="V1.0 1" id="ac365129-eb7f-49ee-8285-7bc7905f4f96" mediaType="application/json"><con:settings><con:setting id="com.eviware.soapui.impl.wsdl.WsdlRequest@request-headers">&lt;xml-fragment/></con:setting></con:settings><con:endpoint>http://development.mawashi.tools:8080</con:endpoint><con:request/><con:originalUri>http://development.mawashi.tools/api/rest/v1.0/</con:originalUri><con:assertion type="Valid HTTP Status Codes" id="14518723-7be8-42c0-b2a0-7f65233a586c" name="Valid HTTP Status Codes"><con:configuration><codes>200</codes></con:configuration></con:assertion><con:assertion type="JsonPath Count" id="13adcb20-8f9e-44da-b413-f1cfe20611af" name="JsonPath Count"><con:configuration/></con:assertion><con:credentials><con:authType>No Authorization</con:authType></con:credentials><con:jmsConfig JMSDeliveryMode="PERSISTENT"/><con:jmsPropertyConfig/><con:parameters><entry key="Authorization" value="{&quot;success&quot;:true,&quot;error&quot;:null,&quot;data&quot;:{&quot;accessToken&quot;:&quot;eyJhbGciOiJIUzUxMiJ9.eyJzdWIiOiI3NyIsImlhdCI6MTU4ODA3MjM2NCwiZXhwIjoxNTg4Njc3MTY0fQ.zA80Nvmnk_0oGQnkMEzG8zpYQ3HdY6_bixJBMKpU4GfBMnhrsqtZpt4kvpGCZD0mQsRFvxWKQSserOCeex34Wg&quot;,&quot;tokenType&quot;:&quot;Bearer&quot;}}" xmlns="http://eviware.com/soapui/config"/></con:parameters><con:parameterOrder><con:entry>Authorization</con:entry></con:parameterOrder></con:restRequest></con:config></con:testStep><con:testStep type="transfer" name="Property Transfer3" id="62da691a-56d1-44ab-a6d9-6009df5cb4af"><con:settings/><con:config xsi:type="con:PropertyTransfersStep" xmlns:xsi="http://www.w3.org/2001/XMLSchema-instance"><con:transfers setNullOnMissingSource="true" transferTextContent="true" failOnError="true" ignoreEmpty="false" transferToAll="false" entitize="false" transferChildNodes="false"><con:name>Bearer</con:name><con:sourceType>Response</con:sourceType><con:sourceStep>V1.0 1</con:sourceStep><con:targetType>Authorization</con:targetType><con:targetStep>app/projects</con:targetStep><con:type>JSONPATH</con:type><con:targetTransferType>JSONPATH</con:targetTransferType><con:upgraded>true</con:upgraded></con:transfers></con:config></con:testStep><con:testStep type="restrequest" name="app/projects" id="f6a7aa4b-76ad-4e89-a4ee-160ed39dc772"><con:settings/><con:config service="http://development.mawashi.tools:8080" resourcePath="/api/rest/v1.0/app/projects" methodName="Method 1" xsi:type="con:RestRequestStep" xmlns:xsi="http://www.w3.org/2001/XMLSchema-instance"><con:restRequest name="app/projects" id="ec00c046-5148-4ad7-8216-02e449a7c89a" mediaType="application/json"><con:settings><con:setting id="com.eviware.soapui.impl.wsdl.WsdlRequest@request-headers">&lt;xml-fragment/></con:setting></con:settings><con:endpoint>http://development.mawashi.tools:8080</con:endpoint><con:request/><con:originalUri>http://development.mawashi.tools/api/rest/v1.0/app/projects</con:originalUri><con:assertion type="Valid HTTP Status Codes" id="5f602bd0-e7ab-4bb4-ae89-a06ebe42001d" name="Valid HTTP Status Codes"><con:configuration><codes>200</codes></con:configuration></con:assertion><con:credentials><con:authType>No Authorization</con:authType></con:credentials><con:jmsConfig JMSDeliveryMode="PERSISTENT"/><con:jmsPropertyConfig/><con:parameters><entry key="Authorization" value="{&quot;success&quot;:false,&quot;error&quot;:&quot;Full authentication is required to access this resource&quot;,&quot;data&quot;:null}" xmlns="http://eviware.com/soapui/config"/></con:parameters></con:restRequest></con:config></con:testStep><con:properties/></con:testCase><con:properties/></con:testSuite><con:properties/><con:wssContainer/><con:oAuth2ProfileContainer/><con:oAuth1ProfileContainer/></con:soapui-project>